vf1.py
VF_1-1.0.0.dist-info/LICENSE
VF_1-1.0.0.dist-info/METADATA
VF_1-1.0.0.dist-info/WHEEL
VF_1-1.0.0.dist-info/entry_points.txt
VF_1-1.0.0.dist-info/top_level.txt
VF_1-1.0.0.dist-info/RECORD
