Metadata-Version: 2.1
Name: VF-1
Version: 1.0.0
Summary: Command line gopher client
Author-email: Solderpunk <solderpunk@posteo.net>
Project-URL: Repository, https://git.sr.ht/~solderpunk/VF-1
Classifier: License :: OSI Approved :: BSD License
Classifier: Programming Language :: Python :: 3 :: Only
Classifier: Topic :: Communications
Classifier: Intended Audience :: End Users/Desktop
Classifier: Environment :: Console
Classifier: Development Status :: 5 - Production/Stable
License-File: LICENSE
Provides-Extra: chardet
Requires-Dist: chardet; extra == "chardet"
